README.md
setup.cfg
setup.py
loop_listen/__init__.py
loop_listen/loop_listen.py
loop_listen.egg-info/PKG-INFO
loop_listen.egg-info/SOURCES.txt
loop_listen.egg-info/dependency_links.txt
loop_listen.egg-info/requires.txt
loop_listen.egg-info/top_level.txt