Metadata-Version: 1.1
Name: loop-listen
Version: 0.1.2
Summary: Create a Audio Handle to keep listening your microphone and saving in wav type files
Home-page: https://github.com/netoolii/loop-listen
Author: Wilson Neto
Author-email: netow@myself.com
License: MIT
Download-URL: https://github.com/netoolii/loop-listen/archive/v0.1.2.tar.gz
Keywords: Audio Loop,Listen,Open Mic,Mic Audio Loop,Audio Handle,pyaudio,wav file,Loop Mic
Platform: UNKNOWN
Classifier: Development Status :: 3 - Alpha
Classifier: Intended Audience :: Developers
Classifier: Topic :: Software Development :: Build Tools
Classifier: License :: OSI Approved :: MIT License
Classifier: Programming Language :: Python :: 3
Classifier: Programming Language :: Python :: 3.4
Classifier: Programming Language :: Python :: 3.5
Classifier: Programming Language :: Python :: 3.6
